Metadata-Version: 2.1
Name: fluxo
Version: 0.14.2
Summary: Simple data flow with execution in separate threads and easy scheduling configuration.
Author-email: Mailson Náscin <mailson.nascin@gmail.com>
License: MIT
Project-URL: Homepage, https://github.com/nascin/fluxo
Project-URL: Source Code, https://github.com/nascin/fluxo
Project-URL: Bug Tracker, https://github.com/nascin/fluxo/issues
Keywords: fluxo,data,scheduler
Classifier: Programming Language :: Python :: 3
Classifier: Intended Audience :: Developers
Classifier: License :: OSI Approved :: MIT License
Classifier: Operating System :: OS Independent
Classifier: Topic :: Software Development :: Internationalization
Requires-Python: >=3.11
License-File: LICENSE
Requires-Dist: flet ==0.15.0
Requires-Dist: schedule ==1.2.1
